texpy/__init__.py
texpy/latex.py
texpy/test.py
texpy-1.0.3.dist-info/LICENSE.txt
texpy-1.0.3.dist-info/METADATA
texpy-1.0.3.dist-info/WHEEL
texpy-1.0.3.dist-info/top_level.txt
texpy-1.0.3.dist-info/RECORD
