Metadata-Version: 2.1
Name: texpy
Version: 1.0.3
Summary: Funzioni utili per lab3
Home-page: https://github.com/Francesco215/menzalib
Author: ['Lorenzo Cavuoti', 'Francesco Sacco']
Author-email: francesco215@live.it
License: UNKNOWN
Platform: UNKNOWN
Classifier: Programming Language :: Python :: 3
Classifier: Operating System :: OS Independent
Requires-Dist: numpy
